CHANGELOG.rst
LICENSE.txt
MANIFEST.in
README.rst
TODO.rst
VERSION.txt
setup.cfg
setup.py
raspi_gpioctl/__init__.py
raspi_gpioctl/cli.py
raspi_gpioctl.egg-info/PKG-INFO
raspi_gpioctl.egg-info/SOURCES.txt
raspi_gpioctl.egg-info/dependency_links.txt
raspi_gpioctl.egg-info/entry_points.txt
raspi_gpioctl.egg-info/requires.txt
raspi_gpioctl.egg-info/top_level.txt
raspi_gpioctl.egg-info/zip-safe