Metadata-Version: 1.1
Name: raspi-gpioctl
Version: 0.0.2
Summary: Raspberry Pi GPIO pin state controller
Home-page: http://github.com/metagriffin/raspi-gpioctl
Author: metagriffin
Author-email: mg.pypi@metagriffin.net
License: GPLv3+
Keywords: raspberry pi pin state controller
Platform: any
Classifier: Development Status :: 4 - Beta
Classifier: Environment :: Other Environment
Classifier: Natural Language :: English
Classifier: Operating System :: Other OS
Classifier: Programming Language :: Python
Classifier: Intended Audience :: System Administrators
Classifier: Topic :: Home Automation
Classifier: Topic :: Utilities
Classifier: License :: OSI Approved :: GNU General Public License v3 or later (GPLv3+)
